{
  "built_at": "2024-05-05T15:18:32.498651-07:00",
  "entries": [
    {
      "Name": "Attributes.mods",
      "Checksum": "dd7ccba02502105daac701a0360f8030157d7b1e",
      "Size": 64427945
    },
    {
      "Name": "Attributes02.mods",
      "Checksum": "3af18f6426290b4cb570c2a4dabb7b1a6ecb0c08",
      "Size": 25328025
    },
    {
      "Name": "Cars.mods",
      "Checksum": "0e583db8469dc19305bb80a439b98ecc1667291f",
      "Size": 75432178
    },
    {
      "Name": "Cars_Small.mods",
      "Checksum": "e471fcb953eac208079d108d6c6bc51c1bc75ec4",
      "Size": 83525373
    },
    {
      "Name": "Cars_Small02.mods",
      "Checksum": "43721ed6c2ad56afdf0ceec227376baefe03713c",
      "Size": 51099652
    },
    {
      "Name": "Cars02.mods",
      "Checksum": "724a9d4dbc77f38e91de330cb89c88e96c203b14",
      "Size": 52766253
    },
    {
      "Name": "Cars03.mods",
      "Checksum": "b3446a9c6fd4bccc45773bb94275cea4be77d9a0",
      "Size": 59149071
    },
    {
      "Name": "Cars04.mods",
      "Checksum": "1ba8de4bb526fb2961b9756d00406a81a8ca57e4",
      "Size": 78061465
    },
    {
      "Name": "Cars05.mods",
      "Checksum": "110569f60177e1cd31f7e9d3f60ebeafeebf5659",
      "Size": 100511481
    },
    {
      "Name": "Cars06.mods",
      "Checksum": "231e2100803dffca92dff744cb6785e79be08a7b",
      "Size": 75771633
    },
    {
      "Name": "Cars07.mods",
      "Checksum": "cdb16faa71def8d60289cf988f982b30dd95d9d6",
      "Size": 9207477
    },
    {
      "Name": "GFX.mods",
      "Checksum": "140bf84130b7db9212f2eab25c338325e0c6dbea",
      "Size": 26645244
    },
    {
      "Name": "Languages.mods",
      "Checksum": "78af430e0fb2b203333738da7bcfe05512869bfd",
      "Size": 6602278
    },
    {
      "Name": "scripts.mods",
      "Checksum": "2be89f7567147fd1fd56e7ca726f698882cc541d",
      "Size": 85316
    },
    {
      "Name": "Sound.mods",
      "Checksum": "fca425cb0706666475bf2119efe0b4578a96de33",
      "Size": 70279067
    },
    {
      "Name": "Sound02.mods",
      "Checksum": "85c3ac1c2ffe5292e95ad5d1376ebd04df8de928",
      "Size": 84037943
    },
    {
      "Name": "Sound03.mods",
      "Checksum": "a537ced5d8a28c35a2d86f5488798365d277aafa",
      "Size": 104399592
    },
    {
      "Name": "Sound04.mods",
      "Checksum": "d68ae410259fc9b275da46dfe3e4910749a999c7",
      "Size": 85388007
    },
    {
      "Name": "Sound05.mods",
      "Checksum": "c17c36011307d197417b6e20386b801629c32f17",
      "Size": 2736861
    },
    {
      "Name": "Sound06.mods",
      "Checksum": "bd0a65f5cc5d0c2297ed8e4db8a127c04d26f590",
      "Size": 9639163
    },
    {
      "Name": "Sound07.mods",
      "Checksum": "94e1d59fc36feb0271cd91e2bb527e63659e77b2",
      "Size": 77434924
    },
    {
      "Name": "Sound08.mods",
      "Checksum": "fb459eb7da2d8f0a48c9b60833eb8d260ae73f49",
      "Size": 58221124
    },
    {
      "Name": "Sound09.mods",
      "Checksum": "3bfd44316617747a7a6e8e8f7067e57b5a48cc1c",
      "Size": 79955248
    },
    {
      "Name": "Sound10.mods",
      "Checksum": "360fd13b2dc1799c8e4cc7901d8a9fdce116b3d6",
      "Size": 25485134
    },
    {
      "Name": "Sound11.mods",
      "Checksum": "aaf73fb1643c5ef0d99ff20221ea7c3c46ddc079",
      "Size": 19206230
    },
    {
      "Name": "Extras.mods",
      "Checksum": "9138a55fdea40a8a29b521749f64357364bee5c5",
      "Size": 2377504
    },
    {
      "Name": "Extras2.mods",
      "Checksum": "34276cc684a224eb015ee7fe6d7b9e43ef30aa53",
      "Size": 23386720
    },
    {
      "Name": "Spoilers.mods",
      "Checksum": "3640b739b5bd6f0b0445bdc5e52609dbd6058388",
      "Size": 1810494
    },
    {
      "Name": "Vinyls.mods",
      "Checksum": "9dee401a42eebc4ccafa3c2e716bc8b4c318e748",
      "Size": 7810
    }
  ]
}