{
  "built_at": "2021-11-17T18:18:27.6189285-07:00",
  "entries": [
    {
      "Name": "Attributes.mods",
      "Checksum": "c8d525f0f4443ee10d4cda264dac0e847478e615",
      "Size": 61649398
    },
    {
      "Name": "Attributes02.mods",
      "Checksum": "30f2f1fb217e4336b205a7e29de3e5bce097b28d",
      "Size": 2776818
    },
    {
      "Name": "Cars.mods",
      "Checksum": "404eb583cea02b15e0936f440e0d8f0a81e18b53",
      "Size": 78626258
    },
    {
      "Name": "Cars02.mods",
      "Checksum": "b8e8f550b695c599f9e291b80036b75d7478e25d",
      "Size": 52845898
    },
    {
      "Name": "Cars03.mods",
      "Checksum": "82ce75c06d63d414f64ea485528fc87f6cb09f96",
      "Size": 60652265
    },
    {
      "Name": "Cars04.mods",
      "Checksum": "c38878298b7047ede57fef11eb3a2c8c95223fca",
      "Size": 74628361
    },
    {
      "Name": "GFX.mods",
      "Checksum": "435f6d2e387601f0991e20850a4fe0ef8696a45a",
      "Size": 2271
    },
    {
      "Name": "Languages.mods",
      "Checksum": "1cf6d4ddf3c2df3799ebff8bd594fcc504088368",
      "Size": 606907
    },
    {
      "Name": "scripts.mods",
      "Checksum": "100761e445ac0c87ec5aa881f02182ff9373bd2e",
      "Size": 19421
    },
    {
      "Name": "Sound.mods",
      "Checksum": "77dc2e7bc8d5d6846fc1c9030fb9e14fcb2f2aca",
      "Size": 75059187
    },
    {
      "Name": "Sound02.mods",
      "Checksum": "db96e003659c22db5019375c2813001324eb0602",
      "Size": 50987806
    },
    {
      "Name": "Sound03.mods",
      "Checksum": "d9a0c1b0620a3d6467dc8f4e322bf35351ccd6c8",
      "Size": 20147606
    }
  ]
}