{
  "built_at": "2022-10-29T13:53:37.5624133-07:00",
  "entries": [
    {
      "Name": "Attributes.mods",
      "Checksum": "0dcc87961a9fc6e2e86f0c2be7f1a5a647268803",
      "Size": 84691949
    },
    {
      "Name": "Attributes02.mods",
      "Checksum": "caf6d4122414c3a9d00bb2f379a71c9ace3fe1e4",
      "Size": 2883411
    },
    {
      "Name": "Cars.mods",
      "Checksum": "34552e670f24480a5ade3b8ccc681c5452eef111",
      "Size": 76711308
    },
    {
      "Name": "Cars_Small.mods",
      "Checksum": "dc302b3f5bb442df0b6e6a13e0175c0d3953fd8c",
      "Size": 82742380
    },
    {
      "Name": "Cars_Small02.mods",
      "Checksum": "43721ed6c2ad56afdf0ceec227376baefe03713c",
      "Size": 51099652
    },
    {
      "Name": "Cars02.mods",
      "Checksum": "cd3c1c77abbfc54a5819994ea6a431c4e7e4ca32",
      "Size": 50894490
    },
    {
      "Name": "Cars03.mods",
      "Checksum": "b3446a9c6fd4bccc45773bb94275cea4be77d9a0",
      "Size": 59149071
    },
    {
      "Name": "Cars04.mods",
      "Checksum": "f6970a8de5a4532d842d6b8873fead72b23f836e",
      "Size": 78061468
    },
    {
      "Name": "Cars05.mods",
      "Checksum": "21d809215e0fa23aa93da8c34a7aba6c0eb75a25",
      "Size": 61448232
    },
    {
      "Name": "GFX.mods",
      "Checksum": "9418573388eb309d129926cfac34016db86c8875",
      "Size": 22831824
    },
    {
      "Name": "Languages.mods",
      "Checksum": "18ea1cdb83028298c4469acbfec3acf4c71f7cb9",
      "Size": 6512438
    },
    {
      "Name": "scripts.mods",
      "Checksum": "100761e445ac0c87ec5aa881f02182ff9373bd2e",
      "Size": 19421
    },
    {
      "Name": "Sound.mods",
      "Checksum": "aa3d9049e53b829a3ba7c9776540ada9053d0245",
      "Size": 77085115
    },
    {
      "Name": "Sound02.mods",
      "Checksum": "5b15ddc2bdeb9e3e4658a0c129980b8e8d23fc8d",
      "Size": 81844473
    },
    {
      "Name": "Sound03.mods",
      "Checksum": "e8df346c2b4837c3e0899b8dbed693e14692bf17",
      "Size": 103348505
    },
    {
      "Name": "Sound04.mods",
      "Checksum": "9f2f2d70709380166ec2bb1604799e3f7d6c6c1e",
      "Size": 67300405
    },
    {
      "Name": "Sound05.mods",
      "Checksum": "a41049ea9bd4f341822cd2bc6b3072203cbcf781",
      "Size": 2790759
    },
    {
      "Name": "Sound06.mods",
      "Checksum": "6d33adceffee264215c2bb4f922eaefd51a68316",
      "Size": 9882166
    },
    {
      "Name": "Sound07.mods",
      "Checksum": "ac68e3c438984f182adb733669460c67cfea7e14",
      "Size": 68903816
    },
    {
      "Name": "Extras.mods",
      "Checksum": "1aa654bb632377c4bde4b655255547272f7a358b",
      "Size": 2244658
    },
    {
      "Name": "Spoilers.mods",
      "Checksum": "3640b739b5bd6f0b0445bdc5e52609dbd6058388",
      "Size": 1810494
    }
  ]
}